gitit/__init__.py
gitit/__main__.py
gitit/add/__init__.py
gitit/add/add.py
gitit/branch/__init__.py
gitit/branch/branch.py
gitit/commit/__init__.py
gitit/commit/commit.py
gitit/push/__init__.py
gitit/push/push.py
gitit/tag/__init__.py
gitit/tag/tag.py
git_it-0.0.16.dist-info/LICENSE
git_it-0.0.16.dist-info/METADATA
git_it-0.0.16.dist-info/WHEEL
git_it-0.0.16.dist-info/entry_points.txt
git_it-0.0.16.dist-info/top_level.txt
git_it-0.0.16.dist-info/RECORD
