Metadata-Version: 2.1
Name: git-it
Version: 0.0.16
Summary: Insert project description here
Author: Hendrik du Toit
Author-email: hendrik@brightedge.co.za
Classifier: Development Status :: 3 - Alpha
Classifier: Intended Audience :: Developers
Classifier: Topic :: Software Development
Classifier: License :: OSI Approved :: MIT License
Classifier: Programming Language :: Python :: 3.10
License-File: LICENSE
Requires-Dist: beetools
Requires-Dist: gitpython
Requires-Dist: pydantic
